Workbook

Sheet Summary
A1: NBA Game Intelligence — CECS 499 Models A, B, and C
A2: Full 2025-26 season, 1,322 games, previous-calendar-day cutoff. Same games for A, B, and C.
A3: Accuracy = pick the winner before tip. Money = $100 on that pick at a reconstructed closing moneyline (σ=14, 3.75% hold). Those are different questions. Prices are not quoted moneylines and not tickets.
A4: How to read the model sheets: row 2 is the season total. Every game is visible below it.
A6: Approach | B6: Games | C6: Correct | D6: Accuracy | E6: Net P&L | F6: Cash if funded $100/game | G6: ROI
A7: Model A — logistic POST /api/predict | B7: =Model_A!A2 | C7: =Model_A!I2 | D7: =IF(B7=0,"",C7/B7) | E7: =Model_A!L2 | F7: =IF(B7=0,"",B7*100+E7) | G7: =IF(B7=0,"",E7/(B7*100))
A8: Model B — Gemma 4 + 5 retrieval tools, no Model A tool | B8: =Model_B!A2 | C8: =Model_B!I2 | D8: =IF(B8=0,"",C8/B8) | E8: =Model_B!L2 | F8: =IF(B8=0,"",B8*100+E8) | G8: =IF(B8=0,"",E8/(B8*100))
A9: Model C — same as B, plus predict_win_probability (Model A as a tool) | B9: =Model_C!A2 | C9: =Model_C!I2 | D9: =IF(B9=0,"",C9/B9) | E9: =Model_C!L2 | F9: =IF(B9=0,"",B9*100+E9) | G9: =IF(B9=0,"",E9/(B9*100))
A11: What to tell the professor
A12: Hypothesis: C beats A and B. Result: A is best of the three at 65.9% (871/1322). C at 65.1% (860/1322) beats B at 61.5% (813/1322). Giving Gemma Model A as a tool helped versus B. It did not beat the logistic.
A13: All three lose money at $100/game versus reconstructed vig. A is least bad. That is expected: a 3.75% hold makes betting favorites −EV even when you pick most winners.
A14: Prices are reconstructed from the closing spread, not quoted moneylines and not tickets.
A15: Models D and E (market-aware follow-ons) are not part of this CECS 499 submission.
A17: Disagreements on the same 1,322 games
A18: C and A pick different teams | B18: 127
A19: C correct and A wrong / A correct and C wrong | B19: 58 | C19: 69
A20: C and B pick different teams | B20: 327
A21: C correct and B wrong / B correct and C wrong | B21: 187 | C21: 140
A23: Caveat: 5 of 1,322 Model B games also called predict_win_probability (B is specified as retrieval-only). Listed on Methodology. Required retrieval gates still passed on every B/C game.

Sheet Model_A
A1: Game | B1: Date | C1: Away | D1: Home | E1: Cutoff | F1: Actual | G1: P(home) | H1: Pick | I1: Correct | J1: Decimal odds | K1: Stake | L1: Net P&L | M1: Cumulative P&L | N1: Tool calls | O1: Gates passed | P1: Gates failed
A2: =COUNTA(A3:A1324) | G2: =AVERAGE(G3:G1324) | I2: =SUM(I3:I1324) | J2: =AVERAGE(J3:J1324) | K2: =SUM(K3:K1324) | L2: =SUM(L3:L1324) | M2: =M1324 | N2: =AVERAGE(N3:N1324) | O2: =SUM(O3:O1324) | P2: =SUM(P3:P1324)
A3: GSW-LAL-2025-10-21 | B3: 2025-10-21 | C3: GSW | D3: LAL | E3: 2025-10-20 | F3: GSW | G3: 0.598598 | H3: LAL | I3: 0 | J3: 2.2460314 | K3: 100 | L3: -100 | M3: =L3 | N3: 0 | O3: 0 | P3: 0
A4: HOU-OKC-2025-10-21 | B4: 2025-10-21 | C4: HOU | D4: OKC | E4: 2025-10-20 | F4: OKC | G4: 0.520823 | H4: OKC | I4: 1 | J4: 1.4199853 | K4: 100 | L4: 42 | M4: =M3+L4 | N4: 0 | O4: 0 | P4: 0
A5: BRK-CHO-2025-10-22 | B5: 2025-10-22 | C5: BRK | D5: CHO | E5: 2025-10-21 | F5: CHO | G5: 0.415731 | H5: BRK | I5: 0 | J5: 2.7759814 | K5: 100 | L5: -100 | M5: =M4+L5 | N5: 0 | O5: 0 | P5: 0
A6: CLE-NYK-2025-10-22 | B6: 2025-10-22 | C6: CLE | D6: NYK | E6: 2025-10-21 | F6: NYK | G6: 0.619896 | H6: NYK | I6: 1 | J6: 2.1075349 | K6: 100 | L6: 110.75 | M6: =M5+L6 | N6: 0 | O6: 0 | P6: 0
A7: DET-CHI-2025-10-22 | B7: 2025-10-22 | C7: DET | D7: CHI | E7: 2025-10-21 | F7: CHI | G7: 0.509272 | H7: CHI | I7: 1 | J7: 2.3216362 | K7: 100 | L7: 132.16 | M7: =M6+L7 | N7: 0 | O7: 0 | P7: 0
A8: LAC-UTA-2025-10-22 | B8: 2025-10-22 | C8: LAC | D8: UTA | E8: 2025-10-21 | F8: UTA | G8: 0.54323 | H8: UTA | I8: 1 | J8: 3.875501 | K8: 100 | L8: 287.55 | M8: =M7+L8 | N8: 0 | O8: 0 | P8: 0
A9: MIA-ORL-2025-10-22 | B9: 2025-10-22 | C9: MIA | D9: ORL | E9: 2025-10-21 | F9: ORL | G9: 0.634807 | H9: ORL | I9: 1 | J9: 1.3458934 | K9: 100 | L9: 34.59 | M9: =M8+L9 | N9: 0 | O9: 0 | P9: 0
A10: MIN-POR-2025-10-22 | B10: 2025-10-22 | C10: MIN | D10: POR | E10: 2025-10-21 | F10: MIN | G10: 0.595785 | H10: POR | I10: 0 | J10: 2.5775476 | K10: 100 | L10: -100 | M10: =M9+L10 | N10: 0 | O10: 0 | P10: 0
A11: NOP-MEM-2025-10-22 | B11: 2025-10-22 | C11: NOP | D11: MEM | E11: 2025-10-21 | F11: MEM | G11: 0.595401 | H11: MEM | I11: 1 | J11: 1.5737661 | K11: 100 | L11: 57.38 | M11: =M10+L11 | N11: 0 | O11: 0 | P11: 0
A12: PHI-BOS-2025-10-22 | B12: 2025-10-22 | C12: PHI | D12: BOS | E12: 2025-10-21 | F12: PHI | G12: 0.673813 | H12: BOS | I12: 0 | J12: 1.4765225 | K12: 100 | L12: -100 | M12: =M11+L12 | N12: 0 | O12: 0 | P12: 0
A13: SAC-PHO-2025-10-22 | B13: 2025-10-22 | C13: SAC | D13: PHO | E13: 2025-10-21 | F13: PHO | G13: 0.605687 | H13: PHO | I13: 1 | J13: 1.6098968 | K13: 100 | L13: 60.99 | M13: =M12+L13 | N13: 0 | O13: 0 | P13: 0
A14: SAS-DAL-2025-10-22 | B14: 2025-10-22 | C14: SAS | D14: DAL | E14: 2025-10-21 | F14: SAS | G14: 0.595827 | H14: DAL | I14: 0 | J14: 1.6098968 | K14: 100 | L14: -100 | M14: =M13+L14 | N14: 0 | O14: 0 | P14: 0
A15: TOR-ATL-2025-10-22 | B15: 2025-10-22 | C15: TOR | D15: ATL | E15: 2025-10-21 | F15: TOR | G15: 0.530763 | H15: ATL | I15: 0 | J15: 1.4765225 | K15: 100 | L15: -100 | M15: =M14+L15 | N15: 0 | O15: 0 | P15: 0
... A1324: NYK-SAS-2026-06-13 | B1324: 2026-06-13 | C1324: NYK | D1324: SAS | E1324: 2026-06-12 | F1324: NYK | G1324: 0.414678 | H1324: NYK | I1324: 1 | J1324: 2.7759814 | K1324: 100 | L1324: 177.6 | M1324: =M1323+L1324 | N1324: 0 | O1324: 0 | P1324: 0

Sheet Model_B
A1: Game | B1: Date | C1: Away | D1: Home | E1: Cutoff | F1: Actual | G1: P(home) | H1: Pick | I1: Correct | J1: Decimal odds | K1: Stake | L1: Net P&L | M1: Cumulative P&L | N1: Tool calls | O1: Gates passed | P1: Gates failed
A2: =COUNTA(A3:A1324) | G2: =AVERAGE(G3:G1324) | I2: =SUM(I3:I1324) | J2: =AVERAGE(J3:J1324) | K2: =SUM(K3:K1324) | L2: =SUM(L3:L1324) | M2: =M1324 | N2: =AVERAGE(N3:N1324) | O2: =SUM(O3:O1324) | P2: =SUM(P3:P1324)
A3: GSW-LAL-2025-10-21 | B3: 2025-10-21 | C3: GSW | D3: LAL | E3: 2025-10-20 | F3: GSW | G3: 0.48 | H3: GSW | I3: 1 | J3: 1.6884184 | K3: 100 | L3: 68.84 | M3: =L3 | N3: 5 | O3: 5 | P3: 0
A4: HOU-OKC-2025-10-21 | B4: 2025-10-21 | C4: HOU | D4: OKC | E4: 2025-10-20 | F4: OKC | G4: 0.63 | H4: OKC | I4: 1 | J4: 1.4199853 | K4: 100 | L4: 42 | M4: =M3+L4 | N4: 5 | O4: 5 | P4: 0
A5: BRK-CHO-2025-10-22 | B5: 2025-10-22 | C5: BRK | D5: CHO | E5: 2025-10-21 | F5: CHO | G5: 0.48 | H5: BRK | I5: 0 | J5: 2.7759814 | K5: 100 | L5: -100 | M5: =M4+L5 | N5: 5 | O5: 5 | P5: 0
A6: CLE-NYK-2025-10-22 | B6: 2025-10-22 | C6: CLE | D6: NYK | E6: 2025-10-21 | F6: NYK | G6: 0.48 | H6: CLE | I6: 0 | J6: 1.7761611 | K6: 100 | L6: -100 | M6: =M5+L6 | N6: 5 | O6: 5 | P6: 0
A7: DET-CHI-2025-10-22 | B7: 2025-10-22 | C7: DET | D7: CHI | E7: 2025-10-21 | F7: CHI | G7: 0.48 | H7: DET | I7: 0 | J7: 1.6480729 | K7: 100 | L7: -100 | M7: =M6+L7 | N7: 5 | O7: 5 | P7: 0
A8: LAC-UTA-2025-10-22 | B8: 2025-10-22 | C8: LAC | D8: UTA | E8: 2025-10-21 | F8: UTA | G8: 0.48 | H8: LAC | I8: 0 | J8: 1.2829249 | K8: 100 | L8: -100 | M8: =M7+L8 | N8: 5 | O8: 5 | P8: 0
A9: MIA-ORL-2025-10-22 | B9: 2025-10-22 | C9: MIA | D9: ORL | E9: 2025-10-21 | F9: ORL | G9: 0.53 | H9: ORL | I9: 1 | J9: 1.3458934 | K9: 100 | L9: 34.59 | M9: =M8+L9 | N9: 5 | O9: 5 | P9: 0
A10: MIN-POR-2025-10-22 | B10: 2025-10-22 | C10: MIN | D10: POR | E10: 2025-10-21 | F10: MIN | G10: 0.48 | H10: MIN | I10: 1 | J10: 1.5395645 | K10: 100 | L10: 53.96 | M10: =M9+L10 | N10: 5 | O10: 5 | P10: 0
A11: NOP-MEM-2025-10-22 | B11: 2025-10-22 | C11: NOP | D11: MEM | E11: 2025-10-21 | F11: MEM | G11: 0.63 | H11: MEM | I11: 1 | J11: 1.5737661 | K11: 100 | L11: 57.38 | M11: =M10+L11 | N11: 5 | O11: 5 | P11: 0
A12: PHI-BOS-2025-10-22 | B12: 2025-10-22 | C12: PHI | D12: BOS | E12: 2025-10-21 | F12: PHI | G12: 0.63 | H12: BOS | I12: 0 | J12: 1.4765225 | K12: 100 | L12: -100 | M12: =M11+L12 | N12: 5 | O12: 5 | P12: 0
A13: SAC-PHO-2025-10-22 | B13: 2025-10-22 | C13: SAC | D13: PHO | E13: 2025-10-21 | F13: PHO | G13: 0.48 | H13: SAC | I13: 0 | J13: 2.4018705 | K13: 100 | L13: -100 | M13: =M12+L13 | N13: 5 | O13: 5 | P13: 0
A14: SAS-DAL-2025-10-22 | B14: 2025-10-22 | C14: SAS | D14: DAL | E14: 2025-10-21 | F14: SAS | G14: 0.48 | H14: SAS | I14: 1 | J14: 2.4018705 | K14: 100 | L14: 140.19 | M14: =M13+L14 | N14: 5 | O14: 5 | P14: 0
A15: TOR-ATL-2025-10-22 | B15: 2025-10-22 | C15: TOR | D15: ATL | E15: 2025-10-21 | F15: TOR | G15: 0.48 | H15: TOR | I15: 1 | J15: 2.7759814 | K15: 100 | L15: 177.6 | M15: =M14+L15 | N15: 5 | O15: 5 | P15: 0
... A1324: NYK-SAS-2026-06-13 | B1324: 2026-06-13 | C1324: NYK | D1324: SAS | E1324: 2026-06-12 | F1324: NYK | G1324: 0.45 | H1324: NYK | I1324: 1 | J1324: 2.7759814 | K1324: 100 | L1324: 177.6 | M1324: =M1323+L1324 | N1324: 5 | O1324: 5 | P1324: 0

Sheet Model_C
A1: Game | B1: Date | C1: Away | D1: Home | E1: Cutoff | F1: Actual | G1: P(home) | H1: Pick | I1: Correct | J1: Decimal odds | K1: Stake | L1: Net P&L | M1: Cumulative P&L | N1: Tool calls | O1: Gates passed | P1: Gates failed
A2: =COUNTA(A3:A1324) | G2: =AVERAGE(G3:G1324) | I2: =SUM(I3:I1324) | J2: =AVERAGE(J3:J1324) | K2: =SUM(K3:K1324) | L2: =SUM(L3:L1324) | M2: =M1324 | N2: =AVERAGE(N3:N1324) | O2: =SUM(O3:O1324) | P2: =SUM(P3:P1324)
A3: GSW-LAL-2025-10-21 | B3: 2025-10-21 | C3: GSW | D3: LAL | E3: 2025-10-20 | F3: GSW | G3: 0.6 | H3: LAL | I3: 0 | J3: 2.2460314 | K3: 100 | L3: -100 | M3: =L3 | N3: 6 | O3: 6 | P3: 0
A4: HOU-OKC-2025-10-21 | B4: 2025-10-21 | C4: HOU | D4: OKC | E4: 2025-10-20 | F4: OKC | G4: 0.5208 | H4: OKC | I4: 1 | J4: 1.4199853 | K4: 100 | L4: 42 | M4: =M3+L4 | N4: 6 | O4: 6 | P4: 0
A5: BRK-CHO-2025-10-22 | B5: 2025-10-22 | C5: BRK | D5: CHO | E5: 2025-10-21 | F5: CHO | G5: 0.416 | H5: BRK | I5: 0 | J5: 2.7759814 | K5: 100 | L5: -100 | M5: =M4+L5 | N5: 6 | O5: 6 | P5: 0
A6: CLE-NYK-2025-10-22 | B6: 2025-10-22 | C6: CLE | D6: NYK | E6: 2025-10-21 | F6: NYK | G6: 0.62 | H6: NYK | I6: 1 | J6: 2.1075349 | K6: 100 | L6: 110.75 | M6: =M5+L6 | N6: 6 | O6: 6 | P6: 0
A7: DET-CHI-2025-10-22 | B7: 2025-10-22 | C7: DET | D7: CHI | E7: 2025-10-21 | F7: CHI | G7: 0.4907 | H7: DET | I7: 0 | J7: 1.6480729 | K7: 100 | L7: -100 | M7: =M6+L7 | N7: 6 | O7: 6 | P7: 0
A8: LAC-UTA-2025-10-22 | B8: 2025-10-22 | C8: LAC | D8: UTA | E8: 2025-10-21 | F8: UTA | G8: 0.4568 | H8: LAC | I8: 0 | J8: 1.2829249 | K8: 100 | L8: -100 | M8: =M7+L8 | N8: 6 | O8: 6 | P8: 0
A9: MIA-ORL-2025-10-22 | B9: 2025-10-22 | C9: MIA | D9: ORL | E9: 2025-10-21 | F9: ORL | G9: 0.6348 | H9: ORL | I9: 1 | J9: 1.3458934 | K9: 100 | L9: 34.59 | M9: =M8+L9 | N9: 6 | O9: 6 | P9: 0
A10: MIN-POR-2025-10-22 | B10: 2025-10-22 | C10: MIN | D10: POR | E10: 2025-10-21 | F10: MIN | G10: 0.4042 | H10: MIN | I10: 1 | J10: 1.5395645 | K10: 100 | L10: 53.96 | M10: =M9+L10 | N10: 6 | O10: 6 | P10: 0
A11: NOP-MEM-2025-10-22 | B11: 2025-10-22 | C11: NOP | D11: MEM | E11: 2025-10-21 | F11: MEM | G11: 0.6 | H11: MEM | I11: 1 | J11: 1.5737661 | K11: 100 | L11: 57.38 | M11: =M10+L11 | N11: 6 | O11: 6 | P11: 0
A12: PHI-BOS-2025-10-22 | B12: 2025-10-22 | C12: PHI | D12: BOS | E12: 2025-10-21 | F12: PHI | G12: 0.6738 | H12: BOS | I12: 0 | J12: 1.4765225 | K12: 100 | L12: -100 | M12: =M11+L12 | N12: 6 | O12: 6 | P12: 0
A13: SAC-PHO-2025-10-22 | B13: 2025-10-22 | C13: SAC | D13: PHO | E13: 2025-10-21 | F13: PHO | G13: 0.6057 | H13: PHO | I13: 1 | J13: 1.6098968 | K13: 100 | L13: 60.99 | M13: =M12+L13 | N13: 6 | O13: 6 | P13: 0
A14: SAS-DAL-2025-10-22 | B14: 2025-10-22 | C14: SAS | D14: DAL | E14: 2025-10-21 | F14: SAS | G14: 0.596 | H14: DAL | I14: 0 | J14: 1.6098968 | K14: 100 | L14: -100 | M14: =M13+L14 | N14: 6 | O14: 6 | P14: 0
A15: TOR-ATL-2025-10-22 | B15: 2025-10-22 | C15: TOR | D15: ATL | E15: 2025-10-21 | F15: TOR | G15: 0.53 | H15: ATL | I15: 0 | J15: 1.4765225 | K15: 100 | L15: -100 | M15: =M14+L15 | N15: 6 | O15: 6 | P15: 0
... A1324: NYK-SAS-2026-06-13 | B1324: 2026-06-13 | C1324: NYK | D1324: SAS | E1324: 2026-06-12 | F1324: NYK | G1324: 0.415 | H1324: NYK | I1324: 1 | J1324: 2.7759814 | K1324: 100 | L1324: 177.6 | M1324: =M1323+L1324 | N1324: 6 | O1324: 6 | P1324: 0

Sheet Methodology
A1: Methodology
A2: What this workbook is
A3: CECS 499 professor packet for Models A, B, and C only. Every completed 2025-26 game (N=1,322), predicted from the previous calendar day. Models D and E are not in this file.
A5: The three arms
A6: A = logistic regression through POST /api/predict. B = Gemma 4 via Ollama through POST /api/run, five retrieval tools, no betting line, no Model A tool. C = the same as B plus predict_win_probability (Model A as one extra tool). A/B/C never see Vegas. C may agree or disagree with A.
A8: Hypothesis and result
A9: Hypothesis: C beats A and B. Full season: A 871/1322 = 65.9% is best of three. C 860/1322 = 65.1% beats B 813/1322 = 61.5%. Giving the agent Model A helped versus retrieval-only Gemma. It did not beat the logistic.
A11: Money
A12: Every arm bets $100 on its pick every game. Prices are reconstructed from the closing spread (margin sigma = 14, 3.75% hold measured on earlier quoted moneylines). Reproduce with python -m eval.betting --validate. Correlation vs older real moneylines is 0.996. These are not tickets and not quoted 2025-26 moneylines. All three arms lose money; A loses least. Hold makes favorites −EV, so beating 50% does not imply profit.
A14: How Model A was scored
A15: Model A is not in the B/C jsonl. Game-level A rows come from the predictor mass-eval CSV on the same 1,322 game_ids. Decimal odds are the same reconstructed prices used on the B/C rows. Net P&L uses the B/C settlement rule: stake × (decimal − 1) when correct, else −$100, rounded to 2 decimals. That sum is −$2,720.60. The mass-eval CSV stores A P&L to 4 decimals (−$2,720.97); the 37-cent gap is rounding only.
A17: Gating
... A24: B/C checkpoint is local/gitignored: eval/results_actual_ui_full_season.jsonl. A rows: docs/evaluation/full-season-mass-eval.csv. Then PYTHONPATH=vendor python -m eval.build_abc_packet. Do not hand the D/E betting workbook to class.
